libprocess_extensions/__init__.py
libprocess_extensions/alabama_maps/__init__.py
libprocess_extensions/alabama_maps/_process_metadata.py
libprocess_extensions/alabama_maps/_querier.py
libprocess_extensions/alabama_maps/_schema.py
libprocess_extensions/british_library/collection_items/__init__.py
libprocess_extensions/british_library/collection_items/_process_metadata.py
libprocess_extensions/british_library/collection_items/_querier.py
libprocess_extensions/british_library/collection_items/_schema.py
libprocess_extensions/british_library/collection_items/_utils.py
libprocess_extensions/british_library/images_online/__init__.py
libprocess_extensions/british_library/images_online/_process_metadata.py
libprocess_extensions/british_library/images_online/_querier.py
libprocess_extensions/british_library/images_online/_schema.py
libprocess_extensions/british_library/online_gallery/__init__.py
libprocess_extensions/british_library/online_gallery/_process_metadata.py
libprocess_extensions/british_library/online_gallery/_querier.py
libprocess_extensions/british_library/online_gallery/_schema.py
libprocess_extensions/telefact/__init__.py
libprocess_extensions/telefact/_process_metadata.py
libprocess_extensions/telefact/_querier.py
libprocess_extensions/telefact/_schema.py
libprocess_extensions-0.1.0.dist-info/LICENSE
libprocess_extensions-0.1.0.dist-info/METADATA
libprocess_extensions-0.1.0.dist-info/WHEEL
libprocess_extensions-0.1.0.dist-info/RECORD
