Metadata-Version: 2.1
Name: libprocess-extensions
Version: 0.1.0
Summary: 
Author: Yu Zhang
Author-email: yuzhang94@outlook.com
Requires-Python: >=3.10,<3.13
Classifier: Programming Language :: Python :: 3
Classifier: Programming Language :: Python :: 3.10
Classifier: Programming Language :: Python :: 3.11
Requires-Dist: jsonschema (>=4.18.4,<5.0.0)
Requires-Dist: libprocess (>=0.1.3,<0.2.0)
Requires-Dist: libquery-extensions (>=0.1.1,<0.2.0)
Requires-Dist: tqdm (>=4.65.0,<5.0.0)
